botlink/__init__.py
botlink/client.py
appscriptify_botlink-0.1.0.dist-info/METADATA
appscriptify_botlink-0.1.0.dist-info/WHEEL
appscriptify_botlink-0.1.0.dist-info/top_level.txt
appscriptify_botlink-0.1.0.dist-info/RECORD
