Metadata-Version: 2.4
Name: appscriptify-botlink
Version: 0.1.0
Summary: Official Python SDK for Botlink by AppScriptify
Author-email: Vansh Choyal <your@email.com>
License: MIT
Project-URL: Homepage, https://botlink.appscriptify.com
Project-URL: Repository, https://github.com/appscriptify/botlink-sdk
Project-URL: Documentation, https://botlink.appscriptify.com/docs
Requires-Python: >=3.9
Requires-Dist: requests>=2.28.0
